django_settings_custom/__init__.py
django_settings_custom/encryption.py
django_settings_custom/version.py
django_settings_custom/management/__init__.py
django_settings_custom/management/commands/__init__.py
django_settings_custom/management/commands/generate_settings.py
django_settings_custom/tests/__init__.py
django_settings_custom/tests/test_encryption.py
django_settings_custom/tests/test_generate_settings.py
django_settings_custom-1.1.1.dist-info/LICENSE
django_settings_custom-1.1.1.dist-info/METADATA
django_settings_custom-1.1.1.dist-info/WHEEL
django_settings_custom-1.1.1.dist-info/top_level.txt
django_settings_custom-1.1.1.dist-info/RECORD
